Arzbot/__init__.py
RS7bot/__init__.py
oimbot/__init__.py
RS7bot-6.6.7.dist-info/METADATA
RS7bot-6.6.7.dist-info/WHEEL
RS7bot-6.6.7.dist-info/top_level.txt
RS7bot-6.6.7.dist-info/RECORD
